cloudflare_dyndns/__init__.py
cloudflare_dyndns/cache.py
cloudflare_dyndns/cli.py
cloudflare_dyndns/cloudflare.py
cloudflare_dyndns/ip_services.py
cloudflare_dyndns/printer.py
cloudflare_dyndns/types.py
cloudflare_dyndns/updater.py
cloudflare_dyndns-5.4.dist-info/METADATA
cloudflare_dyndns-5.4.dist-info/WHEEL
cloudflare_dyndns-5.4.dist-info/entry_points.txt
cloudflare_dyndns-5.4.dist-info/licenses/LICENSE
cloudflare_dyndns-5.4.dist-info/RECORD
