Metadata-Version: 2.4
Name: cloudflare-dyndns
Version: 5.4
Summary: CloudFlare Dynamic DNS client
Author-email: György Kiss <gyorgy@duck.com>
License-Expression: MIT
License-File: LICENSE
Requires-Python: >=3.11
Requires-Dist: click>=8.1.8
Requires-Dist: httpx>=0.28.1
Requires-Dist: pydantic>=2.10.6
Requires-Dist: truststore>=0.10.0
